[
  {
    "taluka_id": "jafrabad",
    "district_id": "jalna",
    "name_en": "JAFRABAD",
    "name_mr": "",
    "lgd": "04126"
  },
  {
    "taluka_id": "jalna",
    "district_id": "jalna",
    "name_en": "JALNA",
    "name_mr": "",
    "lgd": "04127"
  },
  {
    "taluka_id": "partur",
    "district_id": "jalna",
    "name_en": "PARTUR",
    "name_mr": "",
    "lgd": "04131"
  },
  {
    "taluka_id": "mantha",
    "district_id": "jalna",
    "name_en": "MANTHA",
    "name_mr": "",
    "lgd": "04132"
  },
  {
    "taluka_id": "ghansawangi",
    "district_id": "jalna",
    "name_en": "GHANSAWANGI",
    "name_mr": "",
    "lgd": "04130"
  },
  {
    "taluka_id": "ambad",
    "district_id": "jalna",
    "name_en": "AMBAD",
    "name_mr": "",
    "lgd": "04129"
  },
  {
    "taluka_id": "bhokardan",
    "district_id": "jalna",
    "name_en": "BHOKARDAN",
    "name_mr": "",
    "lgd": "04125"
  },
  {
    "taluka_id": "badnapur",
    "district_id": "jalna",
    "name_en": "BADNAPUR",
    "name_mr": "",
    "lgd": "04128"
  }
]