[
  {
    "village_id": "v-531049",
    "district_id": "washim-502",
    "taluka_id": "manora",
    "name_en": "Wapta",
    "name_mr": "",
    "code": "531049",
    "boundary_file": "/data/boundaries/villages/washim-502/manora.geojson"
  },
  {
    "village_id": "v-531055",
    "district_id": "washim-502",
    "taluka_id": "manora",
    "name_en": "Umardari",
    "name_mr": "",
    "code": "531055",
    "boundary_file": "/data/boundaries/villages/washim-502/manora.geojson"
  },
  {
    "village_id": "v-531054",
    "district_id": "washim-502",
    "taluka_id": "manora",
    "name_en": "Lohara",
    "name_mr": "",
    "code": "531054",
    "boundary_file": "/data/boundaries/villages/washim-502/manora.geojson"
  },
  {
    "village_id": "v-531116",
    "district_id": "washim-502",
    "taluka_id": "manora",
    "name_en": "Shinganapur",
    "name_mr": "",
    "code": "531116",
    "boundary_file": "/data/boundaries/villages/washim-502/manora.geojson"
  },
  {
    "village_id": "v-531059",
    "district_id": "washim-502",
    "taluka_id": "manora",
    "name_en": "Jawala Bk.",
    "name_mr": "",
    "code": "531059",
    "boundary_file": "/data/boundaries/villages/washim-502/manora.geojson"
  },
  {
    "village_id": "v-531115",
    "district_id": "washim-502",
    "taluka_id": "manora",
    "name_en": "Singdoh",
    "name_mr": "",
    "code": "531115",
    "boundary_file": "/data/boundaries/villages/washim-502/manora.geojson"
  },
  {
    "village_id": "v-531058",
    "district_id": "washim-502",
    "taluka_id": "manora",
    "name_en": "Hiwara Bk.",
    "name_mr": "",
    "code": "531058",
    "boundary_file": "/data/boundaries/villages/washim-502/manora.geojson"
  },
  {
    "village_id": "v-531053",
    "district_id": "washim-502",
    "taluka_id": "manora",
    "name_en": "Sawargaon",
    "name_mr": "",
    "code": "531053",
    "boundary_file": "/data/boundaries/villages/washim-502/manora.geojson"
  },
  {
    "village_id": "v-531057",
    "district_id": "washim-502",
    "taluka_id": "manora",
    "name_en": "Asola Bk.",
    "name_mr": "",
    "code": "531057",
    "boundary_file": "/data/boundaries/villages/washim-502/manora.geojson"
  },
  {
    "village_id": "v-531062",
    "district_id": "washim-502",
    "taluka_id": "manora",
    "name_en": "Kondoli",
    "name_mr": "",
    "code": "531062",
    "boundary_file": "/data/boundaries/villages/washim-502/manora.geojson"
  },
  {
    "village_id": "v-531056",
    "district_id": "washim-502",
    "taluka_id": "manora",
    "name_en": "Eklara",
    "name_mr": "",
    "code": "531056",
    "boundary_file": "/data/boundaries/villages/washim-502/manora.geojson"
  },
  {
    "village_id": "v-531118",
    "district_id": "washim-502",
    "taluka_id": "manora",
    "name_en": "Sakhardoh",
    "name_mr": "",
    "code": "531118",
    "boundary_file": "/data/boundaries/villages/washim-502/manora.geojson"
  },
  {
    "village_id": "v-531117",
    "district_id": "washim-502",
    "taluka_id": "manora",
    "name_en": "Rohna",
    "name_mr": "",
    "code": "531117",
    "boundary_file": "/data/boundaries/villages/washim-502/manora.geojson"
  },
  {
    "village_id": "v-531071",
    "district_id": "washim-502",
    "taluka_id": "manora",
    "name_en": "Borwha Bk.",
    "name_mr": "",
    "code": "531071",
    "boundary_file": "/data/boundaries/villages/washim-502/manora.geojson"
  },
  {
    "village_id": "v-531068",
    "district_id": "washim-502",
    "taluka_id": "manora",
    "name_en": "Watod",
    "name_mr": "",
    "code": "531068",
    "boundary_file": "/data/boundaries/villages/washim-502/manora.geojson"
  },
  {
    "village_id": "v-531070",
    "district_id": "washim-502",
    "taluka_id": "manora",
    "name_en": "Talap Bk.",
    "name_mr": "",
    "code": "531070",
    "boundary_file": "/data/boundaries/villages/washim-502/manora.geojson"
  },
  {
    "village_id": "v-531063",
    "district_id": "washim-502",
    "taluka_id": "manora",
    "name_en": "Gundi",
    "name_mr": "",
    "code": "531063",
    "boundary_file": "/data/boundaries/villages/washim-502/manora.geojson"
  },
  {
    "village_id": "v-531060",
    "district_id": "washim-502",
    "taluka_id": "manora",
    "name_en": "Jawala Kh.",
    "name_mr": "",
    "code": "531060",
    "boundary_file": "/data/boundaries/villages/washim-502/manora.geojson"
  },
  {
    "village_id": "v-531061",
    "district_id": "washim-502",
    "taluka_id": "manora",
    "name_en": "Kheda Abai",
    "name_mr": "",
    "code": "531061",
    "boundary_file": "/data/boundaries/villages/washim-502/manora.geojson"
  },
  {
    "village_id": "v-531075",
    "district_id": "washim-502",
    "taluka_id": "manora",
    "name_en": "Yeshawantnagar",
    "name_mr": "",
    "code": "531075",
    "boundary_file": "/data/boundaries/villages/washim-502/manora.geojson"
  },
  {
    "village_id": "v-531119",
    "district_id": "washim-502",
    "taluka_id": "manora",
    "name_en": "Kolar",
    "name_mr": "",
    "code": "531119",
    "boundary_file": "/data/boundaries/villages/washim-502/manora.geojson"
  },
  {
    "village_id": "v-531120",
    "district_id": "washim-502",
    "taluka_id": "manora",
    "name_en": "Halda",
    "name_mr": "",
    "code": "531120",
    "boundary_file": "/data/boundaries/villages/washim-502/manora.geojson"
  },
  {
    "village_id": "v-531064",
    "district_id": "washim-502",
    "taluka_id": "manora",
    "name_en": "Dhamni Manora",
    "name_mr": "",
    "code": "531064",
    "boundary_file": "/data/boundaries/villages/washim-502/manora.geojson"
  },
  {
    "village_id": "v-531106",
    "district_id": "washim-502",
    "taluka_id": "manora",
    "name_en": "Umari Bk.",
    "name_mr": "",
    "code": "531106",
    "boundary_file": "/data/boundaries/villages/washim-502/manora.geojson"
  },
  {
    "village_id": "v-531141",
    "district_id": "washim-502",
    "taluka_id": "manora",
    "name_en": "Someshwar Nagar",
    "name_mr": "",
    "code": "531141",
    "boundary_file": "/data/boundaries/villages/washim-502/manora.geojson"
  },
  {
    "village_id": "v-531108",
    "district_id": "washim-502",
    "taluka_id": "manora",
    "name_en": "Gondegaon.",
    "name_mr": "",
    "code": "531108",
    "boundary_file": "/data/boundaries/villages/washim-502/manora.geojson"
  },
  {
    "village_id": "v-531113",
    "district_id": "washim-502",
    "taluka_id": "manora",
    "name_en": "Vasant Nagar",
    "name_mr": "",
    "code": "531113",
    "boundary_file": "/data/boundaries/villages/washim-502/manora.geojson"
  },
  {
    "village_id": "v-531109",
    "district_id": "washim-502",
    "taluka_id": "manora",
    "name_en": "Wadgaon",
    "name_mr": "",
    "code": "531109",
    "boundary_file": "/data/boundaries/villages/washim-502/manora.geojson"
  },
  {
    "village_id": "v-531110",
    "district_id": "washim-502",
    "taluka_id": "manora",
    "name_en": "Balajinagar",
    "name_mr": "",
    "code": "531110",
    "boundary_file": "/data/boundaries/villages/washim-502/manora.geojson"
  },
  {
    "village_id": "v-531114",
    "district_id": "washim-502",
    "taluka_id": "manora",
    "name_en": "Shendona",
    "name_mr": "",
    "code": "531114",
    "boundary_file": "/data/boundaries/villages/washim-502/manora.geojson"
  },
  {
    "village_id": "v-531112",
    "district_id": "washim-502",
    "taluka_id": "manora",
    "name_en": "Amkinhi",
    "name_mr": "",
    "code": "531112",
    "boundary_file": "/data/boundaries/villages/washim-502/manora.geojson"
  },
  {
    "village_id": "v-531111",
    "district_id": "washim-502",
    "taluka_id": "manora",
    "name_en": "Jotibanagar",
    "name_mr": "",
    "code": "531111",
    "boundary_file": "/data/boundaries/villages/washim-502/manora.geojson"
  },
  {
    "village_id": "v-531072",
    "district_id": "washim-502",
    "taluka_id": "manora",
    "name_en": "Karli",
    "name_mr": "",
    "code": "531072",
    "boundary_file": "/data/boundaries/villages/washim-502/manora.geojson"
  },
  {
    "village_id": "v-531073",
    "district_id": "washim-502",
    "taluka_id": "manora",
    "name_en": "Sewadasnagar",
    "name_mr": "",
    "code": "531073",
    "boundary_file": "/data/boundaries/villages/washim-502/manora.geojson"
  },
  {
    "village_id": "v-531074",
    "district_id": "washim-502",
    "taluka_id": "manora",
    "name_en": "Waroli",
    "name_mr": "",
    "code": "531074",
    "boundary_file": "/data/boundaries/villages/washim-502/manora.geojson"
  },
  {
    "village_id": "v-531021",
    "district_id": "washim-502",
    "taluka_id": "manora",
    "name_en": "Tornala",
    "name_mr": "",
    "code": "531021",
    "boundary_file": "/data/boundaries/villages/washim-502/manora.geojson"
  },
  {
    "village_id": "v-531017",
    "district_id": "washim-502",
    "taluka_id": "manora",
    "name_en": "Umbarda",
    "name_mr": "",
    "code": "531017",
    "boundary_file": "/data/boundaries/villages/washim-502/manora.geojson"
  },
  {
    "village_id": "v-531019",
    "district_id": "washim-502",
    "taluka_id": "manora",
    "name_en": "Jamdara",
    "name_mr": "",
    "code": "531019",
    "boundary_file": "/data/boundaries/villages/washim-502/manora.geojson"
  },
  {
    "village_id": "v-531023",
    "district_id": "washim-502",
    "taluka_id": "manora",
    "name_en": "Chausala",
    "name_mr": "",
    "code": "531023",
    "boundary_file": "/data/boundaries/villages/washim-502/manora.geojson"
  },
  {
    "village_id": "v-531024",
    "district_id": "washim-502",
    "taluka_id": "manora",
    "name_en": "Dahithana",
    "name_mr": "",
    "code": "531024",
    "boundary_file": "/data/boundaries/villages/washim-502/manora.geojson"
  },
  {
    "village_id": "v-531025",
    "district_id": "washim-502",
    "taluka_id": "manora",
    "name_en": "Dapura Bk.",
    "name_mr": "",
    "code": "531025",
    "boundary_file": "/data/boundaries/villages/washim-502/manora.geojson"
  },
  {
    "village_id": "v-531012",
    "district_id": "washim-502",
    "taluka_id": "manora",
    "name_en": "Renkapur",
    "name_mr": "",
    "code": "531012",
    "boundary_file": "/data/boundaries/villages/washim-502/manora.geojson"
  },
  {
    "village_id": "v-531016",
    "district_id": "washim-502",
    "taluka_id": "manora",
    "name_en": "Bidgaon",
    "name_mr": "",
    "code": "531016",
    "boundary_file": "/data/boundaries/villages/washim-502/manora.geojson"
  },
  {
    "village_id": "v-531014",
    "district_id": "washim-502",
    "taluka_id": "manora",
    "name_en": "Ajani",
    "name_mr": "",
    "code": "531014",
    "boundary_file": "/data/boundaries/villages/washim-502/manora.geojson"
  },
  {
    "village_id": "v-531026",
    "district_id": "washim-502",
    "taluka_id": "manora",
    "name_en": "Jamni",
    "name_mr": "",
    "code": "531026",
    "boundary_file": "/data/boundaries/villages/washim-502/manora.geojson"
  },
  {
    "village_id": "v-531029",
    "district_id": "washim-502",
    "taluka_id": "manora",
    "name_en": "Dapura Kh.",
    "name_mr": "",
    "code": "531029",
    "boundary_file": "/data/boundaries/villages/washim-502/manora.geojson"
  },
  {
    "village_id": "v-531015",
    "district_id": "washim-502",
    "taluka_id": "manora",
    "name_en": "Bhandegaon",
    "name_mr": "",
    "code": "531015",
    "boundary_file": "/data/boundaries/villages/washim-502/manora.geojson"
  },
  {
    "village_id": "v-531031",
    "district_id": "washim-502",
    "taluka_id": "manora",
    "name_en": "Gartek",
    "name_mr": "",
    "code": "531031",
    "boundary_file": "/data/boundaries/villages/washim-502/manora.geojson"
  },
  {
    "village_id": "v-531030",
    "district_id": "washim-502",
    "taluka_id": "manora",
    "name_en": "Dara",
    "name_mr": "",
    "code": "531030",
    "boundary_file": "/data/boundaries/villages/washim-502/manora.geojson"
  },
  {
    "village_id": "v-531027",
    "district_id": "washim-502",
    "taluka_id": "manora",
    "name_en": "Dhanora Bhuse",
    "name_mr": "",
    "code": "531027",
    "boundary_file": "/data/boundaries/villages/washim-502/manora.geojson"
  },
  {
    "village_id": "v-531013",
    "district_id": "washim-502",
    "taluka_id": "manora",
    "name_en": "Sayyadpur",
    "name_mr": "",
    "code": "531013",
    "boundary_file": "/data/boundaries/villages/washim-502/manora.geojson"
  },
  {
    "village_id": "v-531028",
    "district_id": "washim-502",
    "taluka_id": "manora",
    "name_en": "Mahamad Shahapur",
    "name_mr": "",
    "code": "531028",
    "boundary_file": "/data/boundaries/villages/washim-502/manora.geojson"
  },
  {
    "village_id": "v-531034",
    "district_id": "washim-502",
    "taluka_id": "manora",
    "name_en": "Bhoyani",
    "name_mr": "",
    "code": "531034",
    "boundary_file": "/data/boundaries/villages/washim-502/manora.geojson"
  },
  {
    "village_id": "v-531032",
    "district_id": "washim-502",
    "taluka_id": "manora",
    "name_en": "Jamuna Kh.",
    "name_mr": "",
    "code": "531032",
    "boundary_file": "/data/boundaries/villages/washim-502/manora.geojson"
  },
  {
    "village_id": "v-531035",
    "district_id": "washim-502",
    "taluka_id": "manora",
    "name_en": "Rudrala",
    "name_mr": "",
    "code": "531035",
    "boundary_file": "/data/boundaries/villages/washim-502/manora.geojson"
  },
  {
    "village_id": "v-531033",
    "district_id": "washim-502",
    "taluka_id": "manora",
    "name_en": "Nainy",
    "name_mr": "",
    "code": "531033",
    "boundary_file": "/data/boundaries/villages/washim-502/manora.geojson"
  },
  {
    "village_id": "v-531036",
    "district_id": "washim-502",
    "taluka_id": "manora",
    "name_en": "Khandala",
    "name_mr": "",
    "code": "531036",
    "boundary_file": "/data/boundaries/villages/washim-502/manora.geojson"
  },
  {
    "village_id": "v-531042",
    "district_id": "washim-502",
    "taluka_id": "manora",
    "name_en": "Chondhi",
    "name_mr": "",
    "code": "531042",
    "boundary_file": "/data/boundaries/villages/washim-502/manora.geojson"
  },
  {
    "village_id": "v-531041",
    "district_id": "washim-502",
    "taluka_id": "manora",
    "name_en": "Khapri",
    "name_mr": "",
    "code": "531041",
    "boundary_file": "/data/boundaries/villages/washim-502/manora.geojson"
  },
  {
    "village_id": "v-531043",
    "district_id": "washim-502",
    "taluka_id": "manora",
    "name_en": "Derdi",
    "name_mr": "",
    "code": "531043",
    "boundary_file": "/data/boundaries/villages/washim-502/manora.geojson"
  },
  {
    "village_id": "v-531038",
    "district_id": "washim-502",
    "taluka_id": "manora",
    "name_en": "Mohgaon",
    "name_mr": "",
    "code": "531038",
    "boundary_file": "/data/boundaries/villages/washim-502/manora.geojson"
  },
  {
    "village_id": "v-531039",
    "district_id": "washim-502",
    "taluka_id": "manora",
    "name_en": "Terka",
    "name_mr": "",
    "code": "531039",
    "boundary_file": "/data/boundaries/villages/washim-502/manora.geojson"
  },
  {
    "village_id": "v-531040",
    "district_id": "washim-502",
    "taluka_id": "manora",
    "name_en": "Wagdari",
    "name_mr": "",
    "code": "531040",
    "boundary_file": "/data/boundaries/villages/washim-502/manora.geojson"
  },
  {
    "village_id": "v-531045",
    "district_id": "washim-502",
    "taluka_id": "manora",
    "name_en": "Kupta",
    "name_mr": "",
    "code": "531045",
    "boundary_file": "/data/boundaries/villages/washim-502/manora.geojson"
  },
  {
    "village_id": "v-531046",
    "district_id": "washim-502",
    "taluka_id": "manora",
    "name_en": "Tembhala",
    "name_mr": "",
    "code": "531046",
    "boundary_file": "/data/boundaries/villages/washim-502/manora.geojson"
  },
  {
    "village_id": "v-531044",
    "district_id": "washim-502",
    "taluka_id": "manora",
    "name_en": "Wanjarkhed",
    "name_mr": "",
    "code": "531044",
    "boundary_file": "/data/boundaries/villages/washim-502/manora.geojson"
  },
  {
    "village_id": "v-531052",
    "district_id": "washim-502",
    "taluka_id": "manora",
    "name_en": "Dhanora Kh.",
    "name_mr": "",
    "code": "531052",
    "boundary_file": "/data/boundaries/villages/washim-502/manora.geojson"
  },
  {
    "village_id": "v-531047",
    "district_id": "washim-502",
    "taluka_id": "manora",
    "name_en": "Hatti",
    "name_mr": "",
    "code": "531047",
    "boundary_file": "/data/boundaries/villages/washim-502/manora.geojson"
  },
  {
    "village_id": "v-531051",
    "district_id": "washim-502",
    "taluka_id": "manora",
    "name_en": "Kamlapur",
    "name_mr": "",
    "code": "531051",
    "boundary_file": "/data/boundaries/villages/washim-502/manora.geojson"
  },
  {
    "village_id": "v-531037",
    "district_id": "washim-502",
    "taluka_id": "manora",
    "name_en": "Jamdara",
    "name_mr": "",
    "code": "531037",
    "boundary_file": "/data/boundaries/villages/washim-502/manora.geojson"
  },
  {
    "village_id": "v-531050",
    "district_id": "washim-502",
    "taluka_id": "manora",
    "name_en": "Mundala",
    "name_mr": "",
    "code": "531050",
    "boundary_file": "/data/boundaries/villages/washim-502/manora.geojson"
  },
  {
    "village_id": "v-531048",
    "district_id": "washim-502",
    "taluka_id": "manora",
    "name_en": "Parawa",
    "name_mr": "",
    "code": "531048",
    "boundary_file": "/data/boundaries/villages/washim-502/manora.geojson"
  },
  {
    "village_id": "v-531065",
    "district_id": "washim-502",
    "taluka_id": "manora",
    "name_en": "Amgavhan",
    "name_mr": "",
    "code": "531065",
    "boundary_file": "/data/boundaries/villages/washim-502/manora.geojson"
  },
  {
    "village_id": "v-531127",
    "district_id": "washim-502",
    "taluka_id": "manora",
    "name_en": "Giroli",
    "name_mr": "",
    "code": "531127",
    "boundary_file": "/data/boundaries/villages/washim-502/manora.geojson"
  },
  {
    "village_id": "v-531066",
    "district_id": "washim-502",
    "taluka_id": "manora",
    "name_en": "Dongargaon",
    "name_mr": "",
    "code": "531066",
    "boundary_file": "/data/boundaries/villages/washim-502/manora.geojson"
  },
  {
    "village_id": "v-531121",
    "district_id": "washim-502",
    "taluka_id": "manora",
    "name_en": "Jagdamba Nagar",
    "name_mr": "",
    "code": "531121",
    "boundary_file": "/data/boundaries/villages/washim-502/manora.geojson"
  },
  {
    "village_id": "v-531122",
    "district_id": "washim-502",
    "taluka_id": "manora",
    "name_en": "Warda",
    "name_mr": "",
    "code": "531122",
    "boundary_file": "/data/boundaries/villages/washim-502/manora.geojson"
  },
  {
    "village_id": "v-531125",
    "district_id": "washim-502",
    "taluka_id": "manora",
    "name_en": "Kherda",
    "name_mr": "",
    "code": "531125",
    "boundary_file": "/data/boundaries/villages/washim-502/manora.geojson"
  },
  {
    "village_id": "v-531076",
    "district_id": "washim-502",
    "taluka_id": "manora",
    "name_en": "Ramtirth",
    "name_mr": "",
    "code": "531076",
    "boundary_file": "/data/boundaries/villages/washim-502/manora.geojson"
  },
  {
    "village_id": "v-531079",
    "district_id": "washim-502",
    "taluka_id": "manora",
    "name_en": "Somthana",
    "name_mr": "",
    "code": "531079",
    "boundary_file": "/data/boundaries/villages/washim-502/manora.geojson"
  },
  {
    "village_id": "v-531083",
    "district_id": "washim-502",
    "taluka_id": "manora",
    "name_en": "Karkheda",
    "name_mr": "",
    "code": "531083",
    "boundary_file": "/data/boundaries/villages/washim-502/manora.geojson"
  },
  {
    "village_id": "v-531128",
    "district_id": "washim-502",
    "taluka_id": "manora",
    "name_en": "Pimpri",
    "name_mr": "",
    "code": "531128",
    "boundary_file": "/data/boundaries/villages/washim-502/manora.geojson"
  },
  {
    "village_id": "v-531123",
    "district_id": "washim-502",
    "taluka_id": "manora",
    "name_en": "Khapardari",
    "name_mr": "",
    "code": "531123",
    "boundary_file": "/data/boundaries/villages/washim-502/manora.geojson"
  },
  {
    "village_id": "v-531067",
    "district_id": "washim-502",
    "taluka_id": "manora",
    "name_en": "Devthana",
    "name_mr": "",
    "code": "531067",
    "boundary_file": "/data/boundaries/villages/washim-502/manora.geojson"
  },
  {
    "village_id": "v-531082",
    "district_id": "washim-502",
    "taluka_id": "manora",
    "name_en": "Vitholi",
    "name_mr": "",
    "code": "531082",
    "boundary_file": "/data/boundaries/villages/washim-502/manora.geojson"
  },
  {
    "village_id": "v-531124",
    "district_id": "washim-502",
    "taluka_id": "manora",
    "name_en": "Girda",
    "name_mr": "",
    "code": "531124",
    "boundary_file": "/data/boundaries/villages/washim-502/manora.geojson"
  },
  {
    "village_id": "v-531078",
    "district_id": "washim-502",
    "taluka_id": "manora",
    "name_en": "Somnathnagar",
    "name_mr": "",
    "code": "531078",
    "boundary_file": "/data/boundaries/villages/washim-502/manora.geojson"
  },
  {
    "village_id": "v-531085",
    "district_id": "washim-502",
    "taluka_id": "manora",
    "name_en": "Dhanora Bk.",
    "name_mr": "",
    "code": "531085",
    "boundary_file": "/data/boundaries/villages/washim-502/manora.geojson"
  },
  {
    "village_id": "v-531126",
    "district_id": "washim-502",
    "taluka_id": "manora",
    "name_en": "Girat",
    "name_mr": "",
    "code": "531126",
    "boundary_file": "/data/boundaries/villages/washim-502/manora.geojson"
  },
  {
    "village_id": "v-531084",
    "district_id": "washim-502",
    "taluka_id": "manora",
    "name_en": "Chikhali",
    "name_mr": "",
    "code": "531084",
    "boundary_file": "/data/boundaries/villages/washim-502/manora.geojson"
  },
  {
    "village_id": "v-531081",
    "district_id": "washim-502",
    "taluka_id": "manora",
    "name_en": "Gavha",
    "name_mr": "",
    "code": "531081",
    "boundary_file": "/data/boundaries/villages/washim-502/manora.geojson"
  },
  {
    "village_id": "v-531130",
    "district_id": "washim-502",
    "taluka_id": "manora",
    "name_en": "Vilegaon",
    "name_mr": "",
    "code": "531130",
    "boundary_file": "/data/boundaries/villages/washim-502/manora.geojson"
  },
  {
    "village_id": "v-531089",
    "district_id": "washim-502",
    "taluka_id": "manora",
    "name_en": "Galamgaon",
    "name_mr": "",
    "code": "531089",
    "boundary_file": "/data/boundaries/villages/washim-502/manora.geojson"
  },
  {
    "village_id": "v-531132",
    "district_id": "washim-502",
    "taluka_id": "manora",
    "name_en": "Bhildongar",
    "name_mr": "",
    "code": "531132",
    "boundary_file": "/data/boundaries/villages/washim-502/manora.geojson"
  },
  {
    "village_id": "v-531088",
    "district_id": "washim-502",
    "taluka_id": "manora",
    "name_en": "Wadgaon",
    "name_mr": "",
    "code": "531088",
    "boundary_file": "/data/boundaries/villages/washim-502/manora.geojson"
  },
  {
    "village_id": "v-531087",
    "district_id": "washim-502",
    "taluka_id": "manora",
    "name_en": "Deurwadi",
    "name_mr": "",
    "code": "531087",
    "boundary_file": "/data/boundaries/villages/washim-502/manora.geojson"
  },
  {
    "village_id": "v-531080",
    "district_id": "washim-502",
    "taluka_id": "manora",
    "name_en": "Asola Kh.",
    "name_mr": "",
    "code": "531080",
    "boundary_file": "/data/boundaries/villages/washim-502/manora.geojson"
  },
  {
    "village_id": "v-531129",
    "district_id": "washim-502",
    "taluka_id": "manora",
    "name_en": "Karpa",
    "name_mr": "",
    "code": "531129",
    "boundary_file": "/data/boundaries/villages/washim-502/manora.geojson"
  },
  {
    "village_id": "v-531086",
    "district_id": "washim-502",
    "taluka_id": "manora",
    "name_en": "Soijana",
    "name_mr": "",
    "code": "531086",
    "boundary_file": "/data/boundaries/villages/washim-502/manora.geojson"
  },
  {
    "village_id": "v-531133",
    "district_id": "washim-502",
    "taluka_id": "manora",
    "name_en": "Khambala",
    "name_mr": "",
    "code": "531133",
    "boundary_file": "/data/boundaries/villages/washim-502/manora.geojson"
  },
  {
    "village_id": "v-531090",
    "district_id": "washim-502",
    "taluka_id": "manora",
    "name_en": "Chakur",
    "name_mr": "",
    "code": "531090",
    "boundary_file": "/data/boundaries/villages/washim-502/manora.geojson"
  },
  {
    "village_id": "v-531092",
    "district_id": "washim-502",
    "taluka_id": "manora",
    "name_en": "Mahuli",
    "name_mr": "",
    "code": "531092",
    "boundary_file": "/data/boundaries/villages/washim-502/manora.geojson"
  },
  {
    "village_id": "v-531138",
    "district_id": "washim-502",
    "taluka_id": "manora",
    "name_en": "Hatoli",
    "name_mr": "",
    "code": "531138",
    "boundary_file": "/data/boundaries/villages/washim-502/manora.geojson"
  },
  {
    "village_id": "v-531135",
    "district_id": "washim-502",
    "taluka_id": "manora",
    "name_en": "Shendurjana (A)",
    "name_mr": "",
    "code": "531135",
    "boundary_file": "/data/boundaries/villages/washim-502/manora.geojson"
  },
  {
    "village_id": "v-531095",
    "district_id": "washim-502",
    "taluka_id": "manora",
    "name_en": "Gadegaon",
    "name_mr": "",
    "code": "531095",
    "boundary_file": "/data/boundaries/villages/washim-502/manora.geojson"
  },
  {
    "village_id": "v-531094",
    "district_id": "washim-502",
    "taluka_id": "manora",
    "name_en": "Panchala",
    "name_mr": "",
    "code": "531094",
    "boundary_file": "/data/boundaries/villages/washim-502/manora.geojson"
  },
  {
    "village_id": "v-531131",
    "district_id": "washim-502",
    "taluka_id": "manora",
    "name_en": "Hiwara Kh.",
    "name_mr": "",
    "code": "531131",
    "boundary_file": "/data/boundaries/villages/washim-502/manora.geojson"
  },
  {
    "village_id": "v-531091",
    "district_id": "washim-502",
    "taluka_id": "manora",
    "name_en": "Bhuli",
    "name_mr": "",
    "code": "531091",
    "boundary_file": "/data/boundaries/villages/washim-502/manora.geojson"
  },
  {
    "village_id": "v-531093",
    "district_id": "washim-502",
    "taluka_id": "manora",
    "name_en": "Hatana",
    "name_mr": "",
    "code": "531093",
    "boundary_file": "/data/boundaries/villages/washim-502/manora.geojson"
  },
  {
    "village_id": "v-531136",
    "district_id": "washim-502",
    "taluka_id": "manora",
    "name_en": "Dhoni",
    "name_mr": "",
    "code": "531136",
    "boundary_file": "/data/boundaries/villages/washim-502/manora.geojson"
  },
  {
    "village_id": "v-531096",
    "district_id": "washim-502",
    "taluka_id": "manora",
    "name_en": "Waigaul",
    "name_mr": "",
    "code": "531096",
    "boundary_file": "/data/boundaries/villages/washim-502/manora.geojson"
  },
  {
    "village_id": "v-531144",
    "district_id": "washim-502",
    "taluka_id": "manora",
    "name_en": "Ujwal Nagar",
    "name_mr": "",
    "code": "531144",
    "boundary_file": "/data/boundaries/villages/washim-502/manora.geojson"
  },
  {
    "village_id": "v-531137",
    "district_id": "washim-502",
    "taluka_id": "manora",
    "name_en": "Amdari",
    "name_mr": "",
    "code": "531137",
    "boundary_file": "/data/boundaries/villages/washim-502/manora.geojson"
  },
  {
    "village_id": "v-531134",
    "district_id": "washim-502",
    "taluka_id": "manora",
    "name_en": "Ingalwadi",
    "name_mr": "",
    "code": "531134",
    "boundary_file": "/data/boundaries/villages/washim-502/manora.geojson"
  },
  {
    "village_id": "v-531143",
    "district_id": "washim-502",
    "taluka_id": "manora",
    "name_en": "Palodi",
    "name_mr": "",
    "code": "531143",
    "boundary_file": "/data/boundaries/villages/washim-502/manora.geojson"
  },
  {
    "village_id": "v-531098",
    "district_id": "washim-502",
    "taluka_id": "manora",
    "name_en": "Naigaon Bandi",
    "name_mr": "",
    "code": "531098",
    "boundary_file": "/data/boundaries/villages/washim-502/manora.geojson"
  },
  {
    "village_id": "v-531099",
    "district_id": "washim-502",
    "taluka_id": "manora",
    "name_en": "Pimpal Shenda",
    "name_mr": "",
    "code": "531099",
    "boundary_file": "/data/boundaries/villages/washim-502/manora.geojson"
  },
  {
    "village_id": "v-531146",
    "district_id": "washim-502",
    "taluka_id": "manora",
    "name_en": "Mendra",
    "name_mr": "",
    "code": "531146",
    "boundary_file": "/data/boundaries/villages/washim-502/manora.geojson"
  },
  {
    "village_id": "v-531145",
    "district_id": "washim-502",
    "taluka_id": "manora",
    "name_en": "Gosta",
    "name_mr": "",
    "code": "531145",
    "boundary_file": "/data/boundaries/villages/washim-502/manora.geojson"
  },
  {
    "village_id": "v-531140",
    "district_id": "washim-502",
    "taluka_id": "manora",
    "name_en": "Fulumari",
    "name_mr": "",
    "code": "531140",
    "boundary_file": "/data/boundaries/villages/washim-502/manora.geojson"
  },
  {
    "village_id": "v-531101",
    "district_id": "washim-502",
    "taluka_id": "manora",
    "name_en": "Vasantnagar (N.V.)",
    "name_mr": "",
    "code": "531101",
    "boundary_file": "/data/boundaries/villages/washim-502/manora.geojson"
  },
  {
    "village_id": "v-531100",
    "district_id": "washim-502",
    "taluka_id": "manora",
    "name_en": "Poharadevi",
    "name_mr": "",
    "code": "531100",
    "boundary_file": "/data/boundaries/villages/washim-502/manora.geojson"
  },
  {
    "village_id": "v-531142",
    "district_id": "washim-502",
    "taluka_id": "manora",
    "name_en": "Rajitnagar",
    "name_mr": "",
    "code": "531142",
    "boundary_file": "/data/boundaries/villages/washim-502/manora.geojson"
  },
  {
    "village_id": "v-531102",
    "district_id": "washim-502",
    "taluka_id": "manora",
    "name_en": "Sawali",
    "name_mr": "",
    "code": "531102",
    "boundary_file": "/data/boundaries/villages/washim-502/manora.geojson"
  },
  {
    "village_id": "v-531139",
    "district_id": "washim-502",
    "taluka_id": "manora",
    "name_en": "Ratanwadi",
    "name_mr": "",
    "code": "531139",
    "boundary_file": "/data/boundaries/villages/washim-502/manora.geojson"
  },
  {
    "village_id": "v-531147",
    "district_id": "washim-502",
    "taluka_id": "manora",
    "name_en": "Vatphal",
    "name_mr": "",
    "code": "531147",
    "boundary_file": "/data/boundaries/villages/washim-502/manora.geojson"
  },
  {
    "village_id": "v-531148",
    "district_id": "washim-502",
    "taluka_id": "manora",
    "name_en": "Rui",
    "name_mr": "",
    "code": "531148",
    "boundary_file": "/data/boundaries/villages/washim-502/manora.geojson"
  },
  {
    "village_id": "v-531107",
    "district_id": "washim-502",
    "taluka_id": "manora",
    "name_en": "Umari Kh.",
    "name_mr": "",
    "code": "531107",
    "boundary_file": "/data/boundaries/villages/washim-502/manora.geojson"
  },
  {
    "village_id": "v-531105",
    "district_id": "washim-502",
    "taluka_id": "manora",
    "name_en": "Gogjai",
    "name_mr": "",
    "code": "531105",
    "boundary_file": "/data/boundaries/villages/washim-502/manora.geojson"
  },
  {
    "village_id": "v-531104",
    "district_id": "washim-502",
    "taluka_id": "manora",
    "name_en": "Kakad Chikhali",
    "name_mr": "",
    "code": "531104",
    "boundary_file": "/data/boundaries/villages/washim-502/manora.geojson"
  },
  {
    "village_id": "v-531103",
    "district_id": "washim-502",
    "taluka_id": "manora",
    "name_en": "Dhawanda",
    "name_mr": "",
    "code": "531103",
    "boundary_file": "/data/boundaries/villages/washim-502/manora.geojson"
  },
  {
    "village_id": "v-531020",
    "district_id": "washim-502",
    "taluka_id": "manora",
    "name_en": "Ghoti",
    "name_mr": "",
    "code": "531020",
    "boundary_file": "/data/boundaries/villages/washim-502/manora.geojson"
  },
  {
    "village_id": "v-531018",
    "district_id": "washim-502",
    "taluka_id": "manora",
    "name_en": "Inzori",
    "name_mr": "",
    "code": "531018",
    "boundary_file": "/data/boundaries/villages/washim-502/manora.geojson"
  },
  {
    "village_id": "v-531022",
    "district_id": "washim-502",
    "taluka_id": "manora",
    "name_en": "Mhasni",
    "name_mr": "",
    "code": "531022",
    "boundary_file": "/data/boundaries/villages/washim-502/manora.geojson"
  },
  {
    "village_id": "v-531097",
    "district_id": "washim-502",
    "taluka_id": "manora",
    "name_en": "Waigul Tanda",
    "name_mr": "",
    "code": "531097",
    "boundary_file": "/data/boundaries/villages/washim-502/manora.geojson"
  },
  {
    "village_id": "v-276294",
    "district_id": "washim-502",
    "taluka_id": "manora",
    "name_en": "Manora (NP)",
    "name_mr": "",
    "code": "276294",
    "boundary_file": "/data/boundaries/villages/washim-502/manora.geojson"
  }
]